setup.py
sync/__init__.py
sync/_version.py
sync/copy.py
sync.egg-info/PKG-INFO
sync.egg-info/SOURCES.txt
sync.egg-info/dependency_links.txt
sync.egg-info/top_level.txt