Metadata-Version: 1.0
Name: sync
Version: 1.0.0
Summary: Python cile copy utility
Home-page: https://github.com/Knio/sync
Author: Tom Flanagan
Author-email: tom@zkpq.ca
License: MIT
Keywords: python file copy
Platform: UNKNOWN
Classifier: Environment :: Console
Classifier: Intended Audience :: Developers
Classifier: Intended Audience :: End Users/Desktop
Classifier: License :: OSI Approved :: MIT License
Classifier: Operating System :: OS Independent
Classifier: Programming Language :: Python
Classifier: Programming Language :: Python :: 2
Classifier: Programming Language :: Python :: 2.7
Classifier: Topic :: Desktop Environment
Classifier: Topic :: Desktop Environment :: File Managers
Classifier: Topic :: System :: Archiving
Classifier: Topic :: System :: Archiving :: Backup
Classifier: Topic :: System :: Archiving :: Mirroring
Classifier: Topic :: Utilities
